lm_buddy/__init__.py
lm_buddy/__main__.py
lm_buddy/buddy.py
lm_buddy/constants.py
lm_buddy/paths.py
lm_buddy/preprocessing.py
lm_buddy/cli/__init__.py
lm_buddy/cli/evaluate.py
lm_buddy/cli/finetune.py
lm_buddy/cli/utils.py
lm_buddy/configs/__init__.py
lm_buddy/configs/common.py
lm_buddy/configs/huggingface.py
lm_buddy/configs/vllm.py
lm_buddy/configs/wandb.py
lm_buddy/configs/jobs/__init__.py
lm_buddy/configs/jobs/common.py
lm_buddy/configs/jobs/finetuning.py
lm_buddy/configs/jobs/hf_evaluate.py
lm_buddy/configs/jobs/lm_harness.py
lm_buddy/configs/jobs/prometheus.py
lm_buddy/configs/jobs/ragas.py
lm_buddy/jobs/__init__.py
lm_buddy/jobs/asset_loader.py
lm_buddy/jobs/common.py
lm_buddy/jobs/finetuning.py
lm_buddy/jobs/model_clients.py
lm_buddy/jobs/utils.py
lm_buddy/jobs/evaluation/__init__.py
lm_buddy/jobs/evaluation/conversation.py
lm_buddy/jobs/evaluation/hf_evaluate.py
lm_buddy/jobs/evaluation/lm_harness.py
lm_buddy/jobs/evaluation/metrics.py
lm_buddy/jobs/evaluation/prometheus.py
lm_buddy/jobs/evaluation/ragas.py
lm_buddy/tracking/__init__.py
lm_buddy/tracking/artifact_utils.py
lm_buddy/tracking/run_utils.py
lm_buddy-0.15.0.dist-info/LICENSE.md
lm_buddy-0.15.0.dist-info/METADATA
lm_buddy-0.15.0.dist-info/WHEEL
lm_buddy-0.15.0.dist-info/entry_points.txt
lm_buddy-0.15.0.dist-info/top_level.txt
lm_buddy-0.15.0.dist-info/RECORD
