Metadata-Version: 2.1
Name: lm-buddy
Version: 0.15.0
Summary: Ray-centric library for finetuning and evaluation of (large) language models.
Author-email: Sean Friedowitz <sean@mozilla.ai>, Aaron Gonzales <aaron@mozilla.ai>, Vicki Boykis <vicki@mozilla.ai>, Davide Eynard <davide@mozilla.ai>, Imtihan Ahmed <imtihan@mozilla.ai>
License: 
Project-URL: Homepage, https://github.com/mozilla-ai/lm-buddy
Project-URL: Repository, https://github.com/mozilla-ai/lm-buddy
Project-URL: Documentation, https://mozilla-ai.github.io/lm-buddy/
Requires-Python: <3.12,>=3.11
License-File: LICENSE.md
Requires-Dist: click>=8.1.7
Requires-Dist: scipy==1.13.1
Requires-Dist: numpy<2.0.0
Requires-Dist: wandb==0.16.3
Requires-Dist: protobuf>=3.20.2
Requires-Dist: urllib3<2,>=1.26.18
Requires-Dist: pydantic>=2.6.4
Requires-Dist: pydantic-yaml>=1.2.0
Requires-Dist: ray[default]==2.30.0
Requires-Dist: loguru==0.7.2
Requires-Dist: s3fs==2024.5.0
Provides-Extra: dev
Requires-Dist: lm-buddy[docs,jobs,ruff,test]; extra == "dev"
Requires-Dist: pre-commit==3.8.0; extra == "dev"
Requires-Dist: jupyter>=1.0.0; extra == "dev"
Provides-Extra: docs
Requires-Dist: Sphinx==7.4.7; extra == "docs"
Requires-Dist: nbsphinx==0.9.4; extra == "docs"
Requires-Dist: sphinx-codeautolink==0.15.2; extra == "docs"
Requires-Dist: myst-parser==3.0.1; extra == "docs"
Requires-Dist: furo==2024.7.18; extra == "docs"
Provides-Extra: jobs
Requires-Dist: torch==2.4.0; extra == "jobs"
Requires-Dist: datasets==2.20.0; extra == "jobs"
Requires-Dist: transformers==4.43.4; extra == "jobs"
Requires-Dist: accelerate==0.33.0; extra == "jobs"
Requires-Dist: peft==0.12.0; extra == "jobs"
Requires-Dist: trl==0.9.6; extra == "jobs"
Requires-Dist: bitsandbytes==0.42.0; extra == "jobs"
Requires-Dist: bert-score==0.3.13; extra == "jobs"
Requires-Dist: lm-eval==0.4.3; extra == "jobs"
Requires-Dist: einops==0.8.0; extra == "jobs"
Requires-Dist: openai==1.38.0; extra == "jobs"
Requires-Dist: ragas==0.1.12; extra == "jobs"
Requires-Dist: langchain-community==0.2.11; extra == "jobs"
Requires-Dist: langchain-openai==0.1.20; extra == "jobs"
Requires-Dist: sentencepiece==0.2.0; extra == "jobs"
Requires-Dist: evaluate==0.4.2; extra == "jobs"
Requires-Dist: mistralai==0.4.2; extra == "jobs"
Provides-Extra: ruff
Requires-Dist: ruff==0.5.5; extra == "ruff"
Provides-Extra: test
Requires-Dist: pytest==8.3.2; extra == "test"
Requires-Dist: pytest-cov==5.0.0; extra == "test"
